pathology
fine_grained_segmentation/__init__.py
fine_grained_segmentation/command_line.py
fine_grained_segmentation/detect.py
fine_grained_segmentation/main.py
fine_grained_segmentation/model.py
fine_grained_segmentation/segmentator.py
fine_grained_segmentation/test_fine_grained_segmentation.py
fine_grained_segmentation/utils.py
fine_grained_segmentation/visualize.py
fine_grained_segmentation-0.1.9.dist-info/LICENSE
fine_grained_segmentation-0.1.9.dist-info/METADATA
fine_grained_segmentation-0.1.9.dist-info/WHEEL
fine_grained_segmentation-0.1.9.dist-info/entry_points.txt
fine_grained_segmentation-0.1.9.dist-info/top_level.txt
fine_grained_segmentation-0.1.9.dist-info/RECORD
