Metadata-Version: 2.1
Name: fine-grained-segmentation
Version: 0.1.9
Summary: Mask R-CNN for Fine-Grained segmentation
Home-page: https://github.com/vinny-palumbo/fine_grained_segmentation
Author: Vincent Palumbo
Author-email: vinnypalumbo.com@gmail.com
License: MIT
Platform: UNKNOWN
Requires-Python: >=3.4
Requires-Dist: matplotlib (==3.0.3)
Requires-Dist: numpy (==1.17.2)
Requires-Dist: scipy (==1.3.1)
Requires-Dist: scikit-image (==0.15.0)
Requires-Dist: onnxruntime (==0.5.0)
